myfirstpackage/__init__.py
myfirstpackage/amir.py
myfirstpackage/amirhossein.py
amirfirstpackage-0.1.2.dist-info/LICENSE.txt
amirfirstpackage-0.1.2.dist-info/METADATA
amirfirstpackage-0.1.2.dist-info/WHEEL
amirfirstpackage-0.1.2.dist-info/top_level.txt
amirfirstpackage-0.1.2.dist-info/RECORD
