Metadata-Version: 2.1
Name: amirfirstpackage
Version: 0.1.2
Summary: Useful tools to work with Elastic stack in Python
Home-page: https://github.com/ncthuc/elastictools
Author: Amirhossein Yousefi
Author-email: amir.usefi75@gmail.com
License: MIT
Download-URL: https://pypi.org/project/elastictools/
Keywords: Elastic,ElasticSearch,ElasticStack
Platform: UNKNOWN
Requires-Dist: elasticsearch (<7.0.0,>=6.0.0)
Requires-Dist: jinja2
